pbaa/__about__.py
pbaa/__init__.py
pbaa/__main__.py
pbaa/cli/__init__.py
pbaa/core/__init__.py
pbaa/core/check.py
pbaa/core/gradio_app.py
pbaa/core/grounded_sam.py
pbaa/core/prerequisite.py
pbaa/core/utils.py
pbaa-1.0.4.dist-info/METADATA
pbaa-1.0.4.dist-info/WHEEL
pbaa-1.0.4.dist-info/entry_points.txt
pbaa-1.0.4.dist-info/licenses/LICENSE.txt
pbaa-1.0.4.dist-info/RECORD
