Metadata-Version: 2.1
Name: pbaa
Version: 1.0.4
Summary: Prompt based automatic annotation
Project-URL: Documentation, https://github.com/dh031200/pbaa#readme
Project-URL: Issues, https://github.com/dh031200/pbaa/issues
Project-URL: Source, https://github.com/dh031200/pbaa
Author-email: dh031200 <imbird0312@gmail.com>
License-Expression: Apache-2.0
License-File: LICENSE.txt
Keywords: Prompt based automatic annotation,grounded-sam,groundingdino,pbaa,segment-anything
Classifier: Development Status :: 4 - Beta
Classifier: Operating System :: POSIX :: Linux
Classifier: Programming Language :: Python
Classifier: Programming Language :: Python :: 3.8
Classifier: Programming Language :: Python :: 3.9
Classifier: Programming Language :: Python :: 3.10
Classifier: Programming Language :: Python :: 3.11
Classifier: Programming Language :: Python :: Implementation :: CPython
Requires-Python: >=3.8
Requires-Dist: click
Requires-Dist: loguru
Requires-Dist: wget
